code_counter/__init__.py
code_counter/__main__.py
code_counter/conf/__init__.py
code_counter/conf/config.json
code_counter/conf/config.py
code_counter/core/__init__.py
code_counter/core/args.py
code_counter/core/counter.py
code_counter/core/visualization.py
code_counter/core/countable/__init__.py
code_counter/core/countable/file.py
code_counter/core/countable/iterator.py
code_counter/tools/__init__.py
code_counter/tools/progress.py
code_counter/tools/request.py
code_counter/tools/singleton.py
code_counter-1.1.1.dist-info/LICENSE
code_counter-1.1.1.dist-info/METADATA
code_counter-1.1.1.dist-info/WHEEL
code_counter-1.1.1.dist-info/entry_points.txt
code_counter-1.1.1.dist-info/top_level.txt
code_counter-1.1.1.dist-info/RECORD
