Metadata-Version: 2.1
Name: code-counter
Version: 1.1.1
Summary: A command-line interface (CLI) utility that can help you easily count code lines and display detailed results.
Home-page: https://github.com/InnoFang/code-counter
Author: Inno Fang
Author-email: innofang@yeah.net
License: Apache License
Project-URL: Documentation, https://github.com/InnoFang/code-counter/blob/master/README.md
Project-URL: Source, https://github.com/InnoFang/code-counter
Project-URL: Bug Reports, https://github.com/InnoFang/code-counter/issues
Keywords: code count line file counter
Platform: UNKNOWN
Classifier: Development Status :: 5 - Production/Stable
Classifier: Intended Audience :: Developers
Classifier: License :: OSI Approved :: Apache Software License
Classifier: Environment :: Console
Classifier: Topic :: Utilities
Classifier: Programming Language :: Python :: 3
Classifier: Programming Language :: Python :: 3.7
Classifier: Programming Language :: Python :: 3.8
Classifier: Programming Language :: Python :: 3.9
Classifier: Programming Language :: Python :: 3.10
Requires-Python: >=3.7
Requires-Dist: matplotlib
Requires-Dist: numpy
